Metadata-Version: 1.1
Name: r53-dyndns
Version: 0.2.0
Summary: Route53 dynamic DNS agent
Home-page: https://github.com/crustymonkey/r53-dyndns
Author: Jay Deiman
Author-email: admin@splitstreams.com
License: UNKNOWN
Platform: UNKNOWN
Classifier: Development Status :: 4 - Beta
Classifier: Environment :: Console
Classifier: Intended Audience :: System Administrators
Classifier: License :: OSI Approved :: GNU General Public License v2 (GPLv2)
Classifier: Natural Language :: English
Classifier: Topic :: Internet :: Name Service (DNS)
Classifier: Operating System :: POSIX
Classifier: Programming Language :: Python
Classifier: Topic :: System :: Systems Administration
